asrbench_cli/__init__.py
asrbench_cli/cli.py
asrbench_cli/commands.py
asrbench_cli/observer.py
asrbench_cli/transcribers/__init__.py
asrbench_cli/transcribers/configs.py
asrbench_cli/transcribers/faster_whisper_.py
asrbench_cli/transcribers/hf_provider.py
asrbench_cli/transcribers/vosk_.py
asrbench_cli/transcribers/wav2vec_.py
asrbench_cli/transcribers/whisper_.py
asrbench_cli-0.1.0.dist-info/entry_points.txt
asrbench_cli-0.1.0.dist-info/LICENSE
asrbench_cli-0.1.0.dist-info/METADATA
asrbench_cli-0.1.0.dist-info/WHEEL
asrbench_cli-0.1.0.dist-info/RECORD
