Metadata-Version: 2.1
Name: asrbench-cli
Version: 0.1.0
Summary: A command-line tool for the ASRBench framework, simplifying audio transcription system benchmarking with a single config file, supporting popular and custom transcription systems
Author: ASRBench
Author-email: asrbenchmark@gmail.com
Requires-Python: >=3.12,<4.0
Classifier: Development Status :: 5 - Production/Stable
Classifier: Environment :: Console
Classifier: Natural Language :: English
Classifier: Operating System :: OS Independent
Classifier: Programming Language :: Python :: 3
Classifier: Programming Language :: Python :: 3.12
Classifier: Topic :: System :: Benchmark
Requires-Dist: asrbench (>=0.1.0,<0.2.0)
Requires-Dist: faster-whisper (>=1.0.3,<2.0.0)
Requires-Dist: librosa (>=0.10.2.post1,<0.11.0)
Requires-Dist: openai-whisper (==20240930)
Requires-Dist: transformers (>=4.44.2,<5.0.0)
Requires-Dist: typer[all] (>=0.13.1,<0.14.0)
Requires-Dist: vosk (>=0.3.45,<0.4.0)
Project-URL: Bug Tracker, https://github.com/ASRBench/asrbench-cli/issues
Project-URL: Documentation, https://asrbench.github.io/asrbench/cli/installation
Project-URL: Source, https://github.com/ASRBench/asrbench-cli
